{
    "configurations": [
        {
            "name": "Linux",
            "includePath": [
                "${workspaceFolder}/**",
                "${workspaceFolder}/src/cpp",
                "/usr/local/include",
                "/home/panos/Applications/libtorch/include/torch/csrc/api/include/",
                "/home/panos/Applications/libtorch/include/torch/csrc/api/include/torch/",
                "/home/panos/Applications/libtorch/include/"
            ],
            "defines": [],
            "compilerPath": "/usr/bin/clang",
            "cStandard": "c17",
            "cppStandard": "c++14",
            "intelliSenseMode": "linux-clang-x64"
        }
    ],
    "version": 4
}